{
	"textures": {
		"0": "mod:block/oak_side",
		"1": "mod:block/oak_top",
		"particle": "mod:block/oak_side"
	},
	"elements": [
		{
			"from": [7, 0, 7],
			"to": [9, 16, 9],
			"rotation": {"angle": 0, "axis": "y", "origin": [15, 8, 15]},
			"faces": {
				"north": {"uv": [13, 0, 16, 16], "texture": "#0"},
				"east": {"uv": [5, 0, 9, 16], "texture": "#0"},
				"south": {"uv": [0, 0, 3, 16], "texture": "#0"},
				"west": {"uv": [0, 0, 4, 16], "texture": "#0"},
				"up": {"uv": [0.945, 1.008, 15.069, 15.069], "texture": "#1"},
				"down": {"uv": [0, 0, 2, 2], "texture": "#0"}
			}
		}
	]
}